[
  {
    "text": "A spider on the camera at Yarramundi Bridge\n[Yarramundi Bridge \\(Agnes Banks\\) traffic camera. A spider is on the camera lens.](https://preview.redd.it/162i6t2xas0g1.png?width=800&format=png&auto=webp&s=7d8082429534fc5ae741a56cf7febce142ef92c5)\n\nThe view from the traffic camera is beautiful this time of year when everything is growing.   \n  \nSpoilered in case someone is afraid of spiders.",
    "suburb": "Agnes Banks",
    "score": 88,
    "created_utc": 1762935160,
    "url": "https://reddit.com/r/sydney/comments/1ouzjja/a_spider_on_the_camera_at_yarramundi_bridge/",
    "type": "post",
    "aspect_query": "bulk"
  },
  {
    "text": "If you're anywhere near West pennant Hills there's a koala sanctuary that  might be nice. And if you have wheels, Agnes Banks Nature reserve a bit further west is a cool pocket of unique ecosystem that we only otherwise see at syd ocean headland areas",
    "suburb": "Agnes Banks",
    "score": 3,
    "created_utc": 1709267392,
    "url": "https://reddit.com/r/sydney/comments/1b3hky3/got_a_day_and_half_to_myself_in_sydney/kst2wff/",
    "type": "comment",
    "aspect_query": "bulk"
  }
]