[
  {
    "text": "Hit it while riding my motorbike through Old Toongabbie.",
    "suburb": "Old Toongabbie",
    "score": 8,
    "created_utc": 1719183501,
    "url": "https://reddit.com/r/sydney/comments/1dmx9bw/looks_like_the_city_misplaced_its_blanket_anyone/l9yz7jv/",
    "type": "comment",
    "aspect_query": "bulk"
  },
  {
    "text": "I had a meme come up in my Facebook that says \"there's a saying  in The Hills.....if there's fog......you're not going to see as far\".  So, yeah, from about Old Toongabbie heading west and north, it's pretty thick where your own headlights blind you.",
    "suburb": "Old Toongabbie",
    "score": 3,
    "created_utc": 1719187059,
    "url": "https://reddit.com/r/sydney/comments/1dmx9bw/looks_like_the_city_misplaced_its_blanket_anyone/l9z7uyh/",
    "type": "comment",
    "aspect_query": "bulk"
  }
]