{
  "suburb": "Dundas Valley",
  "post_count": 4,
  "fetched_at": "2026-04-29T23:35:22.232616+00:00",
  "aspects": {
    "safety": {
      "score": null,
      "mentions": 0,
      "confidence": 0.0,
      "coverage": "none",
      "source": "none"
    },
    "food_and_cafe": {
      "score": null,
      "mentions": 0,
      "confidence": 0.0,
      "coverage": "none",
      "source": "none"
    },
    "nightlife": {
      "score": null,
      "mentions": 0,
      "confidence": 0.0,
      "coverage": "none",
      "source": "none"
    },
    "affordability": {
      "score": null,
      "mentions": 0,
      "confidence": 0.0,
      "coverage": "none",
      "source": "none"
    },
    "transport": {
      "score": null,
      "mentions": 0,
      "confidence": 0.0,
      "coverage": "none",
      "source": "none"
    },
    "community": {
      "score": null,
      "mentions": 0,
      "confidence": 0.0,
      "coverage": "none",
      "source": "none"
    },
    "noise": {
      "score": null,
      "mentions": 0,
      "confidence": 0.0,
      "coverage": "none",
      "source": "none"
    },
    "green_space": {
      "score": 0.0,
      "mentions": 0,
      "confidence": 0.6,
      "coverage": "strong",
      "source": "osm"
    }
  },
  "emotions": {
    "neutral": 0.6132,
    "surprise": 0.0683,
    "sadness": 0.0791,
    "anger": 0.0084,
    "disgust": 0.014,
    "joy": 0.21,
    "fear": 0.007
  },
  "narrative": "Reddit discussions about Dundas Valley are most positive about green space (0.00). Residents are most critical about green space (0.00). This analysis is based on 4 posts and comments. The dominant emotion in community discussions is neutral.",
  "sources": [
    {
      "text": ">Places like Hornsby Heights, St Ives Chase are just extensions of their main suburbs that are on higher terrain / hillier, more residential areas\n\nDundas Valley was named after splitting from Dundas ",
      "url": "https://reddit.com/r/sydney/comments/1bixei5/what_sydney_suburbs_have_taken_their_names_from/kvnrgmh/",
      "score": 18
    },
    {
      "text": "The history of the \"pennant\" hill isn't agreed upon.\n\nI have heard that the pennant was actually at Lauriston House in what is now Dundas Valley. That makes much more sense as you actually get a line ",
      "url": "https://reddit.com/r/sydney/comments/1bixei5/what_sydney_suburbs_have_taken_their_names_from/kvo6eks/",
      "score": 7
    },
    {
      "text": "Dundas Valley is good to go back to The Ponds, because I don't want to be associated with Dundas.",
      "url": "https://reddit.com/r/sydney/comments/19ew546/the_sydney_suburb_of_dumbleton_changed_its_name/kjgb4ws/",
      "score": 5
    },
    {
      "text": "Oh right yeah sorry I meant the Dundas Valley side of the Telopea station, thats getting a bunch of development but it's very early days. The Dundas station is upgraded, and yeah Carlingford still jus",
      "url": "https://reddit.com/r/sydney/comments/1dusfbw/new_parramatta_lr_map_out_confirmed_that_itll_be/lbj8jjl/",
      "score": 2
    }
  ],
  "confidence": 0.133,
  "confidence_tier": "low"
}