{
  "suburb": "Mount Druitt",
  "post_count": 35,
  "fetched_at": "2026-04-18T02:11:11.041058+00:00",
  "aspects": {
    "safety": {
      "score": 0.118,
      "mentions": 12,
      "raw_score": 0.118
    },
    "transport": {
      "score": 0.2,
      "mentions": 4,
      "raw_score": 0.2
    },
    "community": {
      "score": 0.395,
      "mentions": 21,
      "raw_score": 0.395
    },
    "affordability": {
      "score": 0.644,
      "mentions": 5,
      "raw_score": 0.644
    },
    "green_space": {
      "score": 0.844,
      "mentions": 2,
      "raw_score": 0.844
    },
    "noise": {
      "score": 0.988,
      "mentions": 1,
      "raw_score": 0.988
    },
    "nightlife": {
      "score": 0.811,
      "mentions": 2,
      "raw_score": 0.811
    },
    "food_and_cafe": {
      "score": 0.5,
      "mentions": 0,
      "raw_score": 0.5
    }
  },
  "emotions": {
    "anger": 0.0569,
    "disgust": 0.1863,
    "fear": 0.2191,
    "surprise": 0.1277,
    "sadness": 0.0615,
    "neutral": 0.3221,
    "joy": 0.0265
  },
  "narrative": "Reddit discussions about Mount Druitt are most positive about noise (0.99) and green space (0.84). Residents are most critical about transport (0.20) and safety (0.12). This analysis is based on 35 posts and comments. The dominant emotion in community discussions is neutral.",
  "sources": [
    {
      "text": "What the hell\nMOUNT DRUITT IS A SAFE SUBURB?? \n\nThe crime rate is extremely high. My friend got mugged, my other friend had a neighbour who was a drug dealer and had cops do a house raid on him, its a",
      "url": "https://reddit.com/r/sydney/comments/1ixrz3q/what_the_hell/",
      "score": 1201
    },
    {
      "text": "Mount Druitt: Child allegedly raped at knifepoint near train station",
      "url": "https://reddit.com/r/sydney/comments/1exhid6/mount_druitt_child_allegedly_raped_at_knifepoint/",
      "score": 616
    },
    {
      "text": "Your options for late night grocery shopping in Sydney\nMost Colesworths stores in Sydney close at 10pm - we're a bit luckier than Brisbane, where the majority close at 9, but at least they have a 24/7",
      "url": "https://reddit.com/r/sydney/comments/1ghscf0/your_options_for_late_night_grocery_shopping_in/",
      "score": 237
    },
    {
      "text": "Not what you sound like you’re after at all, but if we’re talking a pure sense of community, no joke, Mount Druitt has it.",
      "url": "https://reddit.com/r/sydney/comments/1dio3yd/which_suburbs_or_areas_do_you_think_have_the/l950vtu/",
      "score": 132
    },
    {
      "text": "Climb Mount Druitt",
      "url": "https://reddit.com/r/sydney/comments/1d1i888/here_for_one_week_what_are_weird_places_things_to/l5u7ecr/",
      "score": 100
    },
    {
      "text": "Where do I sign up for housing commission in Surry hills, all my family got was out west in mount druitt",
      "url": "https://reddit.com/r/sydney/comments/1dicx4c/future_of_sydney_live_venue_targeted_by_nimbys_in/l937t6m/",
      "score": 60
    },
    {
      "text": "Police car crashed onto train line between Mount Druitt and Rooty Hill.\nReading reports of a Police Car has gone through the fence approximately 200m on the City side of Mount Druitt station .\nVarious",
      "url": "https://reddit.com/r/sydney/comments/1gcensz/police_car_crashed_onto_train_line_between_mount/",
      "score": 55
    },
    {
      "text": "Intrepid explorer: Climb Mount Druitt",
      "url": "https://reddit.com/r/sydney/comments/1atm1wb/sydney_is_turned_into_an_open_world_game_what/kqym54m/",
      "score": 34
    },
    {
      "text": "TfNSW have been working on 3-4 possible routes to run from Tallawong to St Mary's with potential stops in the new Marsden Park town centre, Bidwill, Dharuk and possibly Mount Druitt (though Mount Drui",
      "url": "https://reddit.com/r/sydney/comments/1bwtb64/sydney_metro_will_tallawong_st_marys_and_westmead/ky8hoi8/",
      "score": 34
    },
    {
      "text": "Climbing to the top of Mount Druitt",
      "url": "https://reddit.com/r/sydney/comments/1cojj2k/what_are_some_experiences_every_sydneysider_has/l3et7vx/",
      "score": 33
    }
  ],
  "confidence": 1.0,
  "confidence_tier": "high"
}