{
  "suburb": "Roseville Chase",
  "post_count": 1,
  "fetched_at": "2026-04-18T02:21:13.122471+00:00",
  "aspects": {
    "community": {
      "score": 0.109,
      "mentions": 1
    },
    "safety": {
      "score": 0.5,
      "mentions": 0
    },
    "food_and_cafe": {
      "score": 0.5,
      "mentions": 0
    },
    "nightlife": {
      "score": 0.5,
      "mentions": 0
    },
    "affordability": {
      "score": 0.5,
      "mentions": 0
    },
    "transport": {
      "score": 0.5,
      "mentions": 0
    },
    "noise": {
      "score": 0.5,
      "mentions": 0
    },
    "green_space": {
      "score": 0.5,
      "mentions": 0
    }
  },
  "emotions": {
    "fear": 0.3676,
    "neutral": 0.3321,
    "anger": 0.1369,
    "sadness": 0.091,
    "surprise": 0.0572,
    "joy": 0.0117,
    "disgust": 0.0035
  },
  "narrative": "Reddit discussions about Roseville Chase are most positive about safety (0.50) and food and cafe (0.50). Residents are most critical about green space (0.50) and community (0.11). This analysis is based on 1 posts and comments. The dominant emotion in community discussions is fear.",
  "sources": [
    {
      "text": "Sydney residents told to save water after major water main burst\nLink: [https://www.smh.com.au/national/nsw/sydney-residents-told-to-save-water-after-major-water-main-burst-20260326-p5zj0y.html](https",
      "url": "https://reddit.com/r/sydney/comments/1s3zv0z/sydney_residents_told_to_save_water_after_major/",
      "score": 251
    }
  ]
}