{
  "suburb": "Woodcroft",
  "post_count": 2,
  "fetched_at": "2026-04-18T02:21:02.831487+00:00",
  "aspects": {
    "green_space": {
      "score": 0.8,
      "mentions": 1
    },
    "community": {
      "score": 0.8,
      "mentions": 1
    },
    "safety": {
      "score": 0.5,
      "mentions": 0
    },
    "food_and_cafe": {
      "score": 0.5,
      "mentions": 0
    },
    "nightlife": {
      "score": 0.5,
      "mentions": 0
    },
    "affordability": {
      "score": 0.5,
      "mentions": 0
    },
    "transport": {
      "score": 0.5,
      "mentions": 0
    },
    "noise": {
      "score": 0.5,
      "mentions": 0
    }
  },
  "emotions": {
    "joy": 0.4529,
    "surprise": 0.0469,
    "neutral": 0.4198,
    "sadness": 0.0166,
    "fear": 0.0228,
    "anger": 0.0291,
    "disgust": 0.0118
  },
  "narrative": "Reddit discussions about Woodcroft are most positive about green space (0.80) and community (0.80). Residents are most critical about transport (0.50) and noise (0.50). This analysis is based on 2 posts and comments. The dominant emotion in community discussions is joy.",
  "sources": [
    {
      "text": "Woodcroft lake\nBeautiful Woodcroft lake yesterday",
      "url": "https://reddit.com/r/sydney/comments/1pxmkac/woodcroft_lake/",
      "score": 31
    },
    {
      "text": "**This is not true.** \n\nThere is a a bunch of rules about naming streets. \n\n[https://www.gnb.nsw.gov.au/road\\_naming](https://www.gnb.nsw.gov.au/road_naming)\n\nFor example in Woodcroft near Doonside th",
      "url": "https://reddit.com/r/sydney/comments/1casrjz/housing_in_the_ponds_western_sydney_australia/l0uyz3k/",
      "score": 9
    }
  ]
}