{
  "suburb": "Woolloomooloo",
  "post_count": 29,
  "fetched_at": "2026-04-29T23:55:03.158375+00:00",
  "aspects": {
    "safety": {
      "score": 0.26,
      "mentions": 7,
      "confidence": 0.7,
      "coverage": "weak",
      "source": "reddit"
    },
    "food_and_cafe": {
      "score": 0.828,
      "mentions": 7,
      "confidence": 0.7,
      "coverage": "weak",
      "source": "reddit"
    },
    "nightlife": {
      "score": 0.845,
      "mentions": 8,
      "confidence": 0.8,
      "coverage": "weak",
      "source": "reddit"
    },
    "affordability": {
      "score": 0.5,
      "mentions": 1,
      "confidence": 0.1,
      "coverage": "weak",
      "source": "reddit"
    },
    "transport": {
      "score": 0.7,
      "mentions": 0,
      "confidence": 0.5,
      "coverage": "weak",
      "source": "arcgis"
    },
    "community": {
      "score": 0.611,
      "mentions": 24,
      "confidence": 1.0,
      "coverage": "weak",
      "source": "reddit"
    },
    "noise": {
      "score": null,
      "mentions": 0,
      "confidence": 0.0,
      "coverage": "none",
      "source": "none"
    },
    "green_space": {
      "score": 0.603,
      "mentions": 0,
      "confidence": 0.6,
      "coverage": "strong",
      "source": "osm"
    }
  },
  "emotions": {
    "neutral": 0.4852,
    "disgust": 0.078,
    "surprise": 0.1129,
    "sadness": 0.0806,
    "fear": 0.077,
    "anger": 0.0216,
    "joy": 0.1447
  },
  "narrative": "Reddit discussions about Woolloomooloo are most positive about nightlife (0.84) and food and cafe (0.83). Residents are most critical about affordability (0.50) and safety (0.26). This analysis is based on 29 posts and comments. The dominant emotion in community discussions is neutral.",
  "sources": [
    {
      "text": "8 people a night sleeping rough in the same spot doesn’t seem any different to what has been happening for the last 10 years.\n\nThere are usually more out front of the Woolloomooloo police station or t",
      "url": "https://reddit.com/r/sydney/comments/1aixdcr/a_makeshift_camp_has_moved_into_one_of_sydneys/koxoqyt/",
      "score": 247
    },
    {
      "text": "Another awesome sunrise over Woolloomooloo",
      "url": "https://reddit.com/r/sydney/comments/1l4a6gp/another_awesome_sunrise_over_woolloomooloo/",
      "score": 193
    },
    {
      "text": "Butler stairs, Potts Point-Woolloomooloo\nThe Butler Stairs are one of the three 19th century stone steps built to link Potts Point/Kings Cross. There is a big grade difference and at the time,  a grea",
      "url": "https://reddit.com/r/sydney/comments/19af6bq/butler_stairs_potts_pointwoolloomooloo/",
      "score": 160
    },
    {
      "text": "Hotels in Sydney with a great pool/bar\nHi I’m in need of some ideas for a staycation in Sydney located in CBD, eastern suburbs or inner city for a few nights in Jan. My husband and I normally always s",
      "url": "https://reddit.com/r/sydney/comments/1hef63e/hotels_in_sydney_with_a_great_poolbar/",
      "score": 48
    },
    {
      "text": "Junkie rams undercover cop car\nThis happened in woolloomooloo on Tuesday. Some junkie decided to ride an office chair down the hill. He hits a car and it turns out to be an undercover cop car. Proceed",
      "url": "https://reddit.com/r/sydney/comments/1pcys49/junkie_rams_undercover_cop_car/",
      "score": 26
    },
    {
      "text": "And Woolloomooloo is the richest of the rich bordered on the poorest of the poor. To be fair they are probably all taking the same drugs.",
      "url": "https://reddit.com/r/sydney/comments/199fwlb/why_do_people_like_to_make_out_that_western/kiey2ik/",
      "score": 22
    },
    {
      "text": "The sheer lack of support for the families in poverty and barely making ends meet.  The number of homeless people who don't get the support they need. \n\nI've worked in Sydney all my adult life, predom",
      "url": "https://reddit.com/r/sydney/comments/1ab9u97/huge_turnout_for_the_invasion_dayaustralia_day/kjmibv0/",
      "score": 18
    },
    {
      "text": "Used to have a 10 metre diving tower and 5 metre then diving boards either side. It was quite deep the Luna Park end. Very different from my days there. Used to walk across the bridge for a swim when ",
      "url": "https://reddit.com/r/sydney/comments/1da5k1g/damn_criminal_what_they_did_to_this_pool/l7i8611/",
      "score": 17
    },
    {
      "text": "He's from Woolloomooloo housing commission",
      "url": "https://reddit.com/r/sydney/comments/199fwlb/why_do_people_like_to_make_out_that_western/kidyjgq/",
      "score": 14
    },
    {
      "text": "How about tramsheds to Woolloomooloo?",
      "url": "https://reddit.com/r/sydney/comments/192ofza/sydney_harbour_walks/kh4i2rs/",
      "score": 7
    }
  ],
  "confidence": 0.967,
  "confidence_tier": "high"
}